problolm/__init__.py
problolm-0.0.0.dist-info/METADATA
problolm-0.0.0.dist-info/WHEEL
problolm-0.0.0.dist-info/top_level.txt
problolm-0.0.0.dist-info/RECORD
