Metadata-Version: 2.4
Name: problolm
Version: 0.0.0
Summary: PR Block LLM - Block low quality PRs generated by LLMs
Author-email: RenChu Wang <patrick1031wang@gmail.com>
License: MIT
Requires-Python: >=3.13
